setup.py
redis_trib.egg-info/PKG-INFO
redis_trib.egg-info/SOURCES.txt
redis_trib.egg-info/dependency_links.txt
redis_trib.egg-info/entry_points.txt
redis_trib.egg-info/not-zip-safe
redis_trib.egg-info/requires.txt
redis_trib.egg-info/top_level.txt
redistrib/__init__.py
redistrib/clusternode.py
redistrib/command.py
redistrib/connection.py
redistrib/console.py
redistrib/exceptions.py