Metadata-Version: 1.0
Name: redis-trib
Version: 0.5.0
Summary: Redis Cluster tools in Python2
Home-page: https://github.com/HunanTV/redis-trib.py
Author: Neuron Teckid
Author-email: lene13@gmail.com
License: MIT
Keywords: Redis Cluster
Platform: UNKNOWN
